pp_weight_estimation/__init__.py
pp_weight_estimation/version.py
pp_weight_estimation/core/__init__.py
pp_weight_estimation/core/function_test.py
pp_weight_estimation/core/function_test_claude.py
pp_weight_estimation/core/function_test_gemini.py
pp_weight_estimation/core/function_test_gpt.py
pp_weight_estimation/core/get_weight.py
pp_weight_estimation/core/gpt_support.py
pp_weight_estimation/core/s3_io.py
pp_weight_estimation/utils/__init__.py
pp_weight_estimation/utils/slack_connect.py
pp_weight_estimation/utils/visulizer.py
pp_weight_estimation-1.1.186.data/scripts/weight_pred.py
pp_weight_estimation-1.1.186.dist-info/METADATA
pp_weight_estimation-1.1.186.dist-info/WHEEL
pp_weight_estimation-1.1.186.dist-info/top_level.txt
pp_weight_estimation-1.1.186.dist-info/RECORD
