Metadata-Version: 2.1
Name: pp_weight_estimation
Version: 1.1.186
Summary: Production planning weight estimation functions
Author: ['Malav Bateriwala']
Requires-Python: >=3.8
Requires-Dist: mb-base
Requires-Dist: mb-utils
Requires-Dist: mb-pandas
